{
    "filename": "geocoded_2016_ngrid(colonial_gas)_repairs_844399e30e6acfc03242d9bbab7722ee.json",
    "leaks_or_repairs": "repairs",
    "results": [
        {
            "address_components": [
                {
                    "long_name": "561",
                    "short_name": "561",
                    "types": [
                        "street_number"
                    ]
                },
                {
                    "long_name": "Hosmer Street",
                    "short_name": "Hosmer St",
                    "types": [
                        "route"
                    ]
                },
                {
                    "long_name": "Marlborough",
                    "short_name": "Marlboro",
                    "types": [
                        "locality",
                        "political"
                    ]
                },
                {
                    "long_name": "Middlesex County",
                    "short_name": "Middlesex County",
                    "types": [
                        "administrative_area_level_2",
                        "political"
                    ]
                },
                {
                    "long_name": "Massachusetts",
                    "short_name": "MA",
                    "types": [
                        "administrative_area_level_1",
                        "political"
                    ]
                },
                {
                    "long_name": "United States",
                    "short_name": "US",
                    "types": [
                        "country",
                        "political"
                    ]
                },
                {
                    "long_name": "01752",
                    "short_name": "01752",
                    "types": [
                        "postal_code"
                    ]
                },
                {
                    "long_name": "1448",
                    "short_name": "1448",
                    "types": [
                        "postal_code_suffix"
                    ]
                }
            ],
            "formatted_address": "561 Hosmer St, Marlborough, MA 01752, USA",
            "geometry": {
                "location": {
                    "lat": 42.3702948,
                    "lng": -71.5315435
                },
                "location_type": "ROOFTOP",
                "viewport": {
                    "northeast": {
                        "lat": 42.3716437802915,
                        "lng": -71.53019451970849
                    },
                    "southwest": {
                        "lat": 42.3689458197085,
                        "lng": -71.53289248029151
                    }
                }
            },
            "partial_match": true,
            "place_id": "ChIJf1AdqI6M44kRFgd5E5YNIE0",
            "types": [
                "street_address"
            ]
        }
    ],
    "row_id": "844399e30e6acfc03242d9bbab7722ee",
    "status": "OK",
    "timestamp": "2017-05-01T17:20:13.986441",
    "utility": "ngrid(colonial_gas)",
    "year": 2016
}