{
    "filename": "geocoded_2016_ngrid(boston_gas)_repairs_2bdc2795dd4a2b9e566441519a6cb231.json",
    "grade": 1,
    "leaks_or_repairs": "repairs",
    "record_date": "2016-05-04T00:00:00",
    "results": [
        {
            "address_components": [
                {
                    "long_name": "400",
                    "short_name": "400",
                    "types": [
                        "street_number"
                    ]
                },
                {
                    "long_name": "West Street",
                    "short_name": "West St",
                    "types": [
                        "route"
                    ]
                },
                {
                    "long_name": "Braintree",
                    "short_name": "Braintree",
                    "types": [
                        "locality",
                        "political"
                    ]
                },
                {
                    "long_name": "Norfolk County",
                    "short_name": "Norfolk County",
                    "types": [
                        "administrative_area_level_2",
                        "political"
                    ]
                },
                {
                    "long_name": "Massachusetts",
                    "short_name": "MA",
                    "types": [
                        "administrative_area_level_1",
                        "political"
                    ]
                },
                {
                    "long_name": "United States",
                    "short_name": "US",
                    "types": [
                        "country",
                        "political"
                    ]
                },
                {
                    "long_name": "02184",
                    "short_name": "02184",
                    "types": [
                        "postal_code"
                    ]
                },
                {
                    "long_name": "3825",
                    "short_name": "3825",
                    "types": [
                        "postal_code_suffix"
                    ]
                }
            ],
            "formatted_address": "400 West St, Braintree, MA 02184, USA",
            "geometry": {
                "bounds": {
                    "northeast": {
                        "lat": 42.21172259999999,
                        "lng": -71.0216104
                    },
                    "southwest": {
                        "lat": 42.2116249,
                        "lng": -71.0217225
                    }
                },
                "location": {
                    "lat": 42.2116738,
                    "lng": -71.0216665
                },
                "location_type": "ROOFTOP",
                "viewport": {
                    "northeast": {
                        "lat": 42.2130227302915,
                        "lng": -71.02031746970849
                    },
                    "southwest": {
                        "lat": 42.2103247697085,
                        "lng": -71.02301543029151
                    }
                }
            },
            "place_id": "ChIJO6g0lUB944kRnkw_0jY1BM4",
            "types": [
                "premise"
            ]
        }
    ],
    "row_id": "2bdc2795dd4a2b9e566441519a6cb231",
    "status": "OK",
    "timestamp": "2017-05-01T16:40:13.735181",
    "utility": "ngrid(boston_gas)",
    "year": 2016
}