{
    "filename": "geocoded_2016_ngrid(boston_gas)_repairs_8fa34f835f70b19c4fe3f77c3a4a9702.json",
    "grade": 2,
    "leaks_or_repairs": "repairs",
    "record_date": "2016-04-22T00:00:00",
    "results": [
        {
            "address_components": [
                {
                    "long_name": "98",
                    "short_name": "98",
                    "types": [
                        "street_number"
                    ]
                },
                {
                    "long_name": "Hadley Street",
                    "short_name": "Hadley St",
                    "types": [
                        "route"
                    ]
                },
                {
                    "long_name": "Malden",
                    "short_name": "Malden",
                    "types": [
                        "locality",
                        "political"
                    ]
                },
                {
                    "long_name": "Middlesex County",
                    "short_name": "Middlesex County",
                    "types": [
                        "administrative_area_level_2",
                        "political"
                    ]
                },
                {
                    "long_name": "Massachusetts",
                    "short_name": "MA",
                    "types": [
                        "administrative_area_level_1",
                        "political"
                    ]
                },
                {
                    "long_name": "United States",
                    "short_name": "US",
                    "types": [
                        "country",
                        "political"
                    ]
                },
                {
                    "long_name": "02148",
                    "short_name": "02148",
                    "types": [
                        "postal_code"
                    ]
                },
                {
                    "long_name": "8005",
                    "short_name": "8005",
                    "types": [
                        "postal_code_suffix"
                    ]
                }
            ],
            "formatted_address": "98 Hadley St, Malden, MA 02148, USA",
            "geometry": {
                "bounds": {
                    "northeast": {
                        "lat": 42.4238057,
                        "lng": -71.0389503
                    },
                    "southwest": {
                        "lat": 42.4237195,
                        "lng": -71.0390551
                    }
                },
                "location": {
                    "lat": 42.4237626,
                    "lng": -71.0390027
                },
                "location_type": "ROOFTOP",
                "viewport": {
                    "northeast": {
                        "lat": 42.4251115802915,
                        "lng": -71.03765371970849
                    },
                    "southwest": {
                        "lat": 42.4224136197085,
                        "lng": -71.0403516802915
                    }
                }
            },
            "place_id": "ChIJ37j1wYdx44kR67WwAdxTrdg",
            "types": [
                "premise"
            ]
        }
    ],
    "row_id": "8fa34f835f70b19c4fe3f77c3a4a9702",
    "status": "OK",
    "timestamp": "2017-05-01T16:45:05.302564",
    "utility": "ngrid(boston_gas)",
    "year": 2016
}