{
    "URI": "https://maps.googleapis.com/maps/api/geocode/json?address=6%20WINCHESTER%20TER%20JAMAICA%20PLAIN%20MA&region=us&components=administrative_area:MA&key=AIzaSyC85ILF1P6-ZBLw2PKmJcd6b7ZyGBsuS20",
    "filename": "geocoded_2016_ngrid_leaks_e2ce21efccb3985168d974f22da879f4.json",
    "leaks_or_repairs": "leaks",
    "original_address": "6 WINCHESTER TER JAMAICA PLAIN MA",
    "results": [
        {
            "address_components": [
                {
                    "long_name": "6",
                    "short_name": "6",
                    "types": [
                        "street_number"
                    ]
                },
                {
                    "long_name": "Winchester Terrace",
                    "short_name": "Winchester Terrace",
                    "types": [
                        "route"
                    ]
                },
                {
                    "long_name": "Jamaica Plain",
                    "short_name": "Jamaica Plain",
                    "types": [
                        "neighborhood",
                        "political"
                    ]
                },
                {
                    "long_name": "Boston",
                    "short_name": "Boston",
                    "types": [
                        "locality",
                        "political"
                    ]
                },
                {
                    "long_name": "Suffolk County",
                    "short_name": "Suffolk County",
                    "types": [
                        "administrative_area_level_2",
                        "political"
                    ]
                },
                {
                    "long_name": "Massachusetts",
                    "short_name": "MA",
                    "types": [
                        "administrative_area_level_1",
                        "political"
                    ]
                },
                {
                    "long_name": "United States",
                    "short_name": "US",
                    "types": [
                        "country",
                        "political"
                    ]
                },
                {
                    "long_name": "02130",
                    "short_name": "02130",
                    "types": [
                        "postal_code"
                    ]
                },
                {
                    "long_name": "3429",
                    "short_name": "3429",
                    "types": [
                        "postal_code_suffix"
                    ]
                }
            ],
            "formatted_address": "6 Winchester Terrace, Jamaica Plain, MA 02130, USA",
            "geometry": {
                "bounds": {
                    "northeast": {
                        "lat": 42.3040887,
                        "lng": -71.12636789999999
                    },
                    "southwest": {
                        "lat": 42.3039643,
                        "lng": -71.1265355
                    }
                },
                "location": {
                    "lat": 42.3040265,
                    "lng": -71.12645169999999
                },
                "location_type": "ROOFTOP",
                "viewport": {
                    "northeast": {
                        "lat": 42.3053754802915,
                        "lng": -71.1251027197085
                    },
                    "southwest": {
                        "lat": 42.3026775197085,
                        "lng": -71.1278006802915
                    }
                }
            },
            "place_id": "ChIJ5xgchT5544kRCRE0EUfdKeM",
            "types": [
                "premise"
            ]
        }
    ],
    "row_id": "e2ce21efccb3985168d974f22da879f4",
    "status": "OK",
    "timestamp": "2017-05-01T15:42:25.504099",
    "utility": "ngrid",
    "year": 2016
}