{
    "filename": "geocoded_2016_ngrid_leaks_b3bd10e3a9a6c50b56de423ec095def1.json",
    "grade": 3,
    "leaks_or_repairs": "leaks",
    "record_date": "2000-08-04T00:00:00",
    "results": [
        {
            "address_components": [
                {
                    "long_name": "Humphrey Street",
                    "short_name": "Humphrey St",
                    "types": [
                        "route"
                    ]
                },
                {
                    "long_name": "Swampscott",
                    "short_name": "Swampscott",
                    "types": [
                        "locality",
                        "political"
                    ]
                },
                {
                    "long_name": "Essex County",
                    "short_name": "Essex County",
                    "types": [
                        "administrative_area_level_2",
                        "political"
                    ]
                },
                {
                    "long_name": "Massachusetts",
                    "short_name": "MA",
                    "types": [
                        "administrative_area_level_1",
                        "political"
                    ]
                },
                {
                    "long_name": "United States",
                    "short_name": "US",
                    "types": [
                        "country",
                        "political"
                    ]
                },
                {
                    "long_name": "01907",
                    "short_name": "01907",
                    "types": [
                        "postal_code"
                    ]
                }
            ],
            "formatted_address": "Humphrey St & Beach Bluff Ave, Swampscott, MA 01907, USA",
            "geometry": {
                "location": {
                    "lat": 42.4802171,
                    "lng": -70.8898452
                },
                "location_type": "APPROXIMATE",
                "viewport": {
                    "northeast": {
                        "lat": 42.48156608029151,
                        "lng": -70.8884962197085
                    },
                    "southwest": {
                        "lat": 42.47886811970851,
                        "lng": -70.8911941802915
                    }
                }
            },
            "place_id": "EjhIdW1waHJleSBTdCAmIEJlYWNoIEJsdWZmIEF2ZSwgU3dhbXBzY290dCwgTUEgMDE5MDcsIFVTQQ",
            "types": [
                "intersection"
            ]
        }
    ],
    "row_id": "b3bd10e3a9a6c50b56de423ec095def1",
    "status": "OK",
    "timestamp": "2017-05-01T15:46:12.687987",
    "utility": "ngrid",
    "year": 2016
}