{
    "URI": "https://maps.googleapis.com/maps/api/geocode/json?address=RAYNOR%20ST%20AND%20CHERRY%20ST%20WHITMAN%20MA&region=us&components=administrative_area:MA&key=AIzaSyC85ILF1P6-ZBLw2PKmJcd6b7ZyGBsuS20",
    "filename": "geocoded_2016_ngrid_leaks_03a03bd094fd274965e923aa55805b27.json",
    "leaks_or_repairs": "leaks",
    "original_address": "RAYNOR ST AND CHERRY ST WHITMAN MA",
    "results": [
        {
            "address_components": [
                {
                    "long_name": "Raynor Avenue",
                    "short_name": "Raynor Ave",
                    "types": [
                        "route"
                    ]
                },
                {
                    "long_name": "Whitman",
                    "short_name": "Whitman",
                    "types": [
                        "locality",
                        "political"
                    ]
                },
                {
                    "long_name": "Plymouth County",
                    "short_name": "Plymouth County",
                    "types": [
                        "administrative_area_level_2",
                        "political"
                    ]
                },
                {
                    "long_name": "Massachusetts",
                    "short_name": "MA",
                    "types": [
                        "administrative_area_level_1",
                        "political"
                    ]
                },
                {
                    "long_name": "United States",
                    "short_name": "US",
                    "types": [
                        "country",
                        "political"
                    ]
                },
                {
                    "long_name": "02382",
                    "short_name": "02382",
                    "types": [
                        "postal_code"
                    ]
                }
            ],
            "formatted_address": "Raynor Ave & Cherry St, Whitman, MA 02382, USA",
            "geometry": {
                "location": {
                    "lat": 42.0868323,
                    "lng": -70.9240903
                },
                "location_type": "APPROXIMATE",
                "viewport": {
                    "northeast": {
                        "lat": 42.08818128029151,
                        "lng": -70.92274131970849
                    },
                    "southwest": {
                        "lat": 42.08548331970851,
                        "lng": -70.9254392802915
                    }
                }
            },
            "partial_match": true,
            "place_id": "Ei5SYXlub3IgQXZlICYgQ2hlcnJ5IFN0LCBXaGl0bWFuLCBNQSAwMjM4MiwgVVNB",
            "types": [
                "intersection"
            ]
        }
    ],
    "row_id": "03a03bd094fd274965e923aa55805b27",
    "status": "OK",
    "timestamp": "2017-05-01T15:47:42.671969",
    "utility": "ngrid",
    "year": 2016
}