{
    "URI": "https://maps.googleapis.com/maps/api/geocode/json?address=177%20CONDOR%20ST%20EAST%20BOSTON%20MA&region=us&components=administrative_area:MA&key=AIzaSyC85ILF1P6-ZBLw2PKmJcd6b7ZyGBsuS20",
    "filename": "geocoded_2016_ngrid(boston_gas)_repairs_e4014f2ed87e7a77ffc42d0fdf7b5c9d.json",
    "leaks_or_repairs": "repairs",
    "original_address": "177 CONDOR ST EAST BOSTON MA",
    "results": [
        {
            "address_components": [
                {
                    "long_name": "177",
                    "short_name": "177",
                    "types": [
                        "street_number"
                    ]
                },
                {
                    "long_name": "Condor Street",
                    "short_name": "Condor St",
                    "types": [
                        "route"
                    ]
                },
                {
                    "long_name": "East Boston",
                    "short_name": "East Boston",
                    "types": [
                        "neighborhood",
                        "political"
                    ]
                },
                {
                    "long_name": "Boston",
                    "short_name": "Boston",
                    "types": [
                        "locality",
                        "political"
                    ]
                },
                {
                    "long_name": "Suffolk County",
                    "short_name": "Suffolk County",
                    "types": [
                        "administrative_area_level_2",
                        "political"
                    ]
                },
                {
                    "long_name": "Massachusetts",
                    "short_name": "MA",
                    "types": [
                        "administrative_area_level_1",
                        "political"
                    ]
                },
                {
                    "long_name": "United States",
                    "short_name": "US",
                    "types": [
                        "country",
                        "political"
                    ]
                },
                {
                    "long_name": "02128",
                    "short_name": "02128",
                    "types": [
                        "postal_code"
                    ]
                },
                {
                    "long_name": "1303",
                    "short_name": "1303",
                    "types": [
                        "postal_code_suffix"
                    ]
                }
            ],
            "formatted_address": "177 Condor St, Boston, MA 02128, USA",
            "geometry": {
                "location": {
                    "lat": 42.382397,
                    "lng": -71.033832
                },
                "location_type": "ROOFTOP",
                "viewport": {
                    "northeast": {
                        "lat": 42.38374598029149,
                        "lng": -71.03248301970851
                    },
                    "southwest": {
                        "lat": 42.3810480197085,
                        "lng": -71.03518098029151
                    }
                }
            },
            "place_id": "ChIJc-8xOUxw44kRPm9csFRwPYw",
            "types": [
                "street_address"
            ]
        }
    ],
    "row_id": "e4014f2ed87e7a77ffc42d0fdf7b5c9d",
    "status": "OK",
    "timestamp": "2017-05-01T16:35:24.311621",
    "utility": "ngrid(boston_gas)",
    "year": 2016
}