{
    "URI": "https://maps.googleapis.com/maps/api/geocode/json?address=19%20MELVIN%20AVE%20LYNN%20MA&region=us&components=administrative_area:MA&key=AIzaSyC85ILF1P6-ZBLw2PKmJcd6b7ZyGBsuS20",
    "filename": "geocoded_2016_ngrid_leaks_f938bba5228334c40956204611f3c8f8.json",
    "leaks_or_repairs": "leaks",
    "original_address": "19 MELVIN AVE LYNN MA",
    "results": [
        {
            "address_components": [
                {
                    "long_name": "19",
                    "short_name": "19",
                    "types": [
                        "street_number"
                    ]
                },
                {
                    "long_name": "Melvin Avenue",
                    "short_name": "Melvin Ave",
                    "types": [
                        "route"
                    ]
                },
                {
                    "long_name": "Lynn",
                    "short_name": "Lynn",
                    "types": [
                        "locality",
                        "political"
                    ]
                },
                {
                    "long_name": "Essex County",
                    "short_name": "Essex County",
                    "types": [
                        "administrative_area_level_2",
                        "political"
                    ]
                },
                {
                    "long_name": "Massachusetts",
                    "short_name": "MA",
                    "types": [
                        "administrative_area_level_1",
                        "political"
                    ]
                },
                {
                    "long_name": "United States",
                    "short_name": "US",
                    "types": [
                        "country",
                        "political"
                    ]
                },
                {
                    "long_name": "01902",
                    "short_name": "01902",
                    "types": [
                        "postal_code"
                    ]
                },
                {
                    "long_name": "1225",
                    "short_name": "1225",
                    "types": [
                        "postal_code_suffix"
                    ]
                }
            ],
            "formatted_address": "19 Melvin Ave, Lynn, MA 01902, USA",
            "geometry": {
                "bounds": {
                    "northeast": {
                        "lat": 42.47739199999999,
                        "lng": -70.9301344
                    },
                    "southwest": {
                        "lat": 42.477263,
                        "lng": -70.93030279999999
                    }
                },
                "location": {
                    "lat": 42.4773275,
                    "lng": -70.9302186
                },
                "location_type": "ROOFTOP",
                "viewport": {
                    "northeast": {
                        "lat": 42.4786764802915,
                        "lng": -70.9288696197085
                    },
                    "southwest": {
                        "lat": 42.4759785197085,
                        "lng": -70.9315675802915
                    }
                }
            },
            "place_id": "ChIJvf7OB7Zs44kRu1WYo-FbW1E",
            "types": [
                "premise"
            ]
        }
    ],
    "row_id": "f938bba5228334c40956204611f3c8f8",
    "status": "OK",
    "timestamp": "2017-05-01T15:33:21.189244",
    "utility": "ngrid",
    "year": 2016
}