{
    "URI": "https://maps.googleapis.com/maps/api/geocode/json?address=74%20OAKRIDGE%20TER%20LYNNFIELD%20MA&region=us&components=administrative_area:MA&key=AIzaSyC85ILF1P6-ZBLw2PKmJcd6b7ZyGBsuS20",
    "filename": "geocoded_2016_ngrid_leaks_906c5174eeadee224984794111d9a111.json",
    "leaks_or_repairs": "leaks",
    "original_address": "74 OAKRIDGE TER LYNNFIELD MA",
    "results": [
        {
            "address_components": [
                {
                    "long_name": "74",
                    "short_name": "74",
                    "types": [
                        "street_number"
                    ]
                },
                {
                    "long_name": "Oak Ridge Terrace",
                    "short_name": "Oak Ridge Terrace",
                    "types": [
                        "route"
                    ]
                },
                {
                    "long_name": "Lynnfield",
                    "short_name": "Lynnfield",
                    "types": [
                        "locality",
                        "political"
                    ]
                },
                {
                    "long_name": "Massachusetts",
                    "short_name": "MA",
                    "types": [
                        "administrative_area_level_1",
                        "political"
                    ]
                },
                {
                    "long_name": "United States",
                    "short_name": "US",
                    "types": [
                        "country",
                        "political"
                    ]
                },
                {
                    "long_name": "01940",
                    "short_name": "01940",
                    "types": [
                        "postal_code"
                    ]
                },
                {
                    "long_name": "1314",
                    "short_name": "1314",
                    "types": [
                        "postal_code_suffix"
                    ]
                }
            ],
            "formatted_address": "74 Oak Ridge Terrace, Lynnfield, MA 01940, USA",
            "geometry": {
                "bounds": {
                    "northeast": {
                        "lat": 42.53086769999999,
                        "lng": -71.02711029999999
                    },
                    "southwest": {
                        "lat": 42.5307514,
                        "lng": -71.02731109999999
                    }
                },
                "location": {
                    "lat": 42.5308096,
                    "lng": -71.02721070000001
                },
                "location_type": "ROOFTOP",
                "viewport": {
                    "northeast": {
                        "lat": 42.5321585302915,
                        "lng": -71.02586171970849
                    },
                    "southwest": {
                        "lat": 42.5294605697085,
                        "lng": -71.0285596802915
                    }
                }
            },
            "partial_match": true,
            "place_id": "ChIJ-w9hvwwN44kR-j71w7QEpDw",
            "types": [
                "premise"
            ]
        }
    ],
    "row_id": "906c5174eeadee224984794111d9a111",
    "status": "OK",
    "timestamp": "2017-05-01T15:44:01.376021",
    "utility": "ngrid",
    "year": 2016
}