{
    "filename": "geocoded_2016_ngrid_leaks_e50a9f72b299dee7224da5b00eaa0a00.json",
    "leaks_or_repairs": "leaks",
    "results": [
        {
            "address_components": [
                {
                    "long_name": "20",
                    "short_name": "20",
                    "types": [
                        "street_number"
                    ]
                },
                {
                    "long_name": "Frank P Bennett Highway",
                    "short_name": "Frank P Bennett Hwy",
                    "types": [
                        "route"
                    ]
                },
                {
                    "long_name": "Saugus",
                    "short_name": "Saugus",
                    "types": [
                        "locality",
                        "political"
                    ]
                },
                {
                    "long_name": "Essex County",
                    "short_name": "Essex County",
                    "types": [
                        "administrative_area_level_2",
                        "political"
                    ]
                },
                {
                    "long_name": "Massachusetts",
                    "short_name": "MA",
                    "types": [
                        "administrative_area_level_1",
                        "political"
                    ]
                },
                {
                    "long_name": "United States",
                    "short_name": "US",
                    "types": [
                        "country",
                        "political"
                    ]
                },
                {
                    "long_name": "01906",
                    "short_name": "01906",
                    "types": [
                        "postal_code"
                    ]
                },
                {
                    "long_name": "4219",
                    "short_name": "4219",
                    "types": [
                        "postal_code_suffix"
                    ]
                }
            ],
            "formatted_address": "20 Frank P Bennett Hwy, Saugus, MA 01906, USA",
            "geometry": {
                "bounds": {
                    "northeast": {
                        "lat": 42.44997,
                        "lng": -71.0230881
                    },
                    "southwest": {
                        "lat": 42.4499661,
                        "lng": -71.02310609999999
                    }
                },
                "location": {
                    "lat": 42.4499661,
                    "lng": -71.0230881
                },
                "location_type": "RANGE_INTERPOLATED",
                "viewport": {
                    "northeast": {
                        "lat": 42.4513170302915,
                        "lng": -71.02174811970848
                    },
                    "southwest": {
                        "lat": 42.4486190697085,
                        "lng": -71.0244460802915
                    }
                }
            },
            "partial_match": true,
            "place_id": "Ei0yMCBGcmFuayBQIEJlbm5ldHQgSHd5LCBTYXVndXMsIE1BIDAxOTA2LCBVU0E",
            "types": [
                "street_address"
            ]
        }
    ],
    "row_id": "e50a9f72b299dee7224da5b00eaa0a00",
    "status": "OK",
    "timestamp": "2017-05-01T15:33:53.958639",
    "utility": "ngrid",
    "year": 2016
}