{
    "URI": "https://maps.googleapis.com/maps/api/geocode/json?address=18%20PLYMOUTH%20ST%20ARLINGTON%20MA&region=us&components=administrative_area:MA&key=AIzaSyC85ILF1P6-ZBLw2PKmJcd6b7ZyGBsuS20",
    "filename": "geocoded_2016_ngrid_leaks_6e626f1f3897205ada2e5af4a5c1ea15.json",
    "leaks_or_repairs": "leaks",
    "original_address": "18 PLYMOUTH ST ARLINGTON MA",
    "results": [
        {
            "address_components": [
                {
                    "long_name": "18",
                    "short_name": "18",
                    "types": [
                        "street_number"
                    ]
                },
                {
                    "long_name": "Plymouth Street",
                    "short_name": "Plymouth St",
                    "types": [
                        "route"
                    ]
                },
                {
                    "long_name": "Arlington",
                    "short_name": "Arlington",
                    "types": [
                        "locality",
                        "political"
                    ]
                },
                {
                    "long_name": "Middlesex County",
                    "short_name": "Middlesex County",
                    "types": [
                        "administrative_area_level_2",
                        "political"
                    ]
                },
                {
                    "long_name": "Massachusetts",
                    "short_name": "MA",
                    "types": [
                        "administrative_area_level_1",
                        "political"
                    ]
                },
                {
                    "long_name": "United States",
                    "short_name": "US",
                    "types": [
                        "country",
                        "political"
                    ]
                },
                {
                    "long_name": "02476",
                    "short_name": "02476",
                    "types": [
                        "postal_code"
                    ]
                },
                {
                    "long_name": "6222",
                    "short_name": "6222",
                    "types": [
                        "postal_code_suffix"
                    ]
                }
            ],
            "formatted_address": "18 Plymouth St, Arlington, MA 02476, USA",
            "geometry": {
                "location": {
                    "lat": 42.4163184,
                    "lng": -71.16578319999999
                },
                "location_type": "ROOFTOP",
                "viewport": {
                    "northeast": {
                        "lat": 42.4176673802915,
                        "lng": -71.16443421970848
                    },
                    "southwest": {
                        "lat": 42.41496941970851,
                        "lng": -71.16713218029149
                    }
                }
            },
            "place_id": "ChIJ-QSQV0h244kRxch4PMiVC00",
            "types": [
                "street_address"
            ]
        }
    ],
    "row_id": "6e626f1f3897205ada2e5af4a5c1ea15",
    "status": "OK",
    "timestamp": "2017-05-01T15:33:00.094674",
    "utility": "ngrid",
    "year": 2016
}