{
    "filename": "geocoded_2016_ngrid_leaks_6df8d986bb8726f8ce635baa94162632.json",
    "grade": 3,
    "leaks_or_repairs": "leaks",
    "record_date": "2012-01-06T00:00:00",
    "results": [
        {
            "address_components": [
                {
                    "long_name": "19",
                    "short_name": "19",
                    "types": [
                        "street_number"
                    ]
                },
                {
                    "long_name": "Park Terrace",
                    "short_name": "Park Terrace",
                    "types": [
                        "route"
                    ]
                },
                {
                    "long_name": "Arlington",
                    "short_name": "Arlington",
                    "types": [
                        "locality",
                        "political"
                    ]
                },
                {
                    "long_name": "Middlesex County",
                    "short_name": "Middlesex County",
                    "types": [
                        "administrative_area_level_2",
                        "political"
                    ]
                },
                {
                    "long_name": "Massachusetts",
                    "short_name": "MA",
                    "types": [
                        "administrative_area_level_1",
                        "political"
                    ]
                },
                {
                    "long_name": "United States",
                    "short_name": "US",
                    "types": [
                        "country",
                        "political"
                    ]
                },
                {
                    "long_name": "02474",
                    "short_name": "02474",
                    "types": [
                        "postal_code"
                    ]
                }
            ],
            "formatted_address": "19 Park Terrace, Arlington, MA 02474, USA",
            "geometry": {
                "location": {
                    "lat": 42.415366,
                    "lng": -71.15103959999999
                },
                "location_type": "ROOFTOP",
                "viewport": {
                    "northeast": {
                        "lat": 42.41671498029149,
                        "lng": -71.14969061970848
                    },
                    "southwest": {
                        "lat": 42.4140170197085,
                        "lng": -71.15238858029149
                    }
                }
            },
            "partial_match": true,
            "place_id": "ChIJiU-Oq1B244kRvd-VjdZhyEg",
            "types": [
                "street_address"
            ]
        }
    ],
    "row_id": "6df8d986bb8726f8ce635baa94162632",
    "status": "OK",
    "timestamp": "2017-05-01T15:33:21.967717",
    "utility": "ngrid",
    "year": 2016
}