{
    "filename": "geocoded_2016_ngrid_leaks_113b55106c793fd15b89cfd606ce2728.json",
    "leaks_or_repairs": "leaks",
    "results": [
        {
            "address_components": [
                {
                    "long_name": "7",
                    "short_name": "7",
                    "types": [
                        "street_number"
                    ]
                },
                {
                    "long_name": "Smith Terrace",
                    "short_name": "Smith Terrace",
                    "types": [
                        "route"
                    ]
                },
                {
                    "long_name": "Braintree",
                    "short_name": "Braintree",
                    "types": [
                        "locality",
                        "political"
                    ]
                },
                {
                    "long_name": "Norfolk County",
                    "short_name": "Norfolk County",
                    "types": [
                        "administrative_area_level_2",
                        "political"
                    ]
                },
                {
                    "long_name": "Massachusetts",
                    "short_name": "MA",
                    "types": [
                        "administrative_area_level_1",
                        "political"
                    ]
                },
                {
                    "long_name": "United States",
                    "short_name": "US",
                    "types": [
                        "country",
                        "political"
                    ]
                },
                {
                    "long_name": "02184",
                    "short_name": "02184",
                    "types": [
                        "postal_code"
                    ]
                }
            ],
            "formatted_address": "7 Smith Terrace, Braintree, MA 02184, USA",
            "geometry": {
                "bounds": {
                    "northeast": {
                        "lat": 42.19262930000001,
                        "lng": -71.00712299999999
                    },
                    "southwest": {
                        "lat": 42.1925445,
                        "lng": -71.0072484
                    }
                },
                "location": {
                    "lat": 42.19258689999999,
                    "lng": -71.0071857
                },
                "location_type": "ROOFTOP",
                "viewport": {
                    "northeast": {
                        "lat": 42.19393588029151,
                        "lng": -71.0058367197085
                    },
                    "southwest": {
                        "lat": 42.19123791970851,
                        "lng": -71.0085346802915
                    }
                }
            },
            "place_id": "ChIJTa5pwlV944kR3aoe6qF1cNg",
            "types": [
                "premise"
            ]
        }
    ],
    "row_id": "113b55106c793fd15b89cfd606ce2728",
    "status": "OK",
    "timestamp": "2017-05-01T15:43:35.015763",
    "utility": "ngrid",
    "year": 2016
}