{
    "filename": "geocoded_2016_ngrid_leaks_ded2e1f87cf8c7e984935df758d58253.json",
    "leaks_or_repairs": "leaks",
    "results": [
        {
            "address_components": [
                {
                    "long_name": "54",
                    "short_name": "54",
                    "types": [
                        "street_number"
                    ]
                },
                {
                    "long_name": "West Ferdinand Street",
                    "short_name": "W Ferdinand St",
                    "types": [
                        "route"
                    ]
                },
                {
                    "long_name": "Stoneham",
                    "short_name": "Stoneham",
                    "types": [
                        "locality",
                        "political"
                    ]
                },
                {
                    "long_name": "Middlesex County",
                    "short_name": "Middlesex County",
                    "types": [
                        "administrative_area_level_2",
                        "political"
                    ]
                },
                {
                    "long_name": "Massachusetts",
                    "short_name": "MA",
                    "types": [
                        "administrative_area_level_1",
                        "political"
                    ]
                },
                {
                    "long_name": "United States",
                    "short_name": "US",
                    "types": [
                        "country",
                        "political"
                    ]
                },
                {
                    "long_name": "02180",
                    "short_name": "02180",
                    "types": [
                        "postal_code"
                    ]
                },
                {
                    "long_name": "4336",
                    "short_name": "4336",
                    "types": [
                        "postal_code_suffix"
                    ]
                }
            ],
            "formatted_address": "54 W Ferdinand St, Stoneham, MA 02180, USA",
            "geometry": {
                "bounds": {
                    "northeast": {
                        "lat": 42.4739438,
                        "lng": -71.0805352
                    },
                    "southwest": {
                        "lat": 42.4739302,
                        "lng": -71.0805386
                    }
                },
                "location": {
                    "lat": 42.4739302,
                    "lng": -71.0805386
                },
                "location_type": "RANGE_INTERPOLATED",
                "viewport": {
                    "northeast": {
                        "lat": 42.4752859802915,
                        "lng": -71.07918791970849
                    },
                    "southwest": {
                        "lat": 42.4725880197085,
                        "lng": -71.0818858802915
                    }
                }
            },
            "partial_match": true,
            "place_id": "Eio1NCBXIEZlcmRpbmFuZCBTdCwgU3RvbmVoYW0sIE1BIDAyMTgwLCBVU0E",
            "types": [
                "street_address"
            ]
        }
    ],
    "row_id": "ded2e1f87cf8c7e984935df758d58253",
    "status": "OK",
    "timestamp": "2017-05-01T15:41:35.773728",
    "utility": "ngrid",
    "year": 2016
}